telepycrypto/__init__.py
telepycrypto/api.py
telepycrypto/exceptions.py
telepycrypto/Types/__init__.py
telepycrypto/Types/invoice.py
telepycrypto/Types/__pycache__/__init__.cpython-38.pyc
telepycrypto/Types/__pycache__/invoice.cpython-38.pyc
telepycrypto-1.0.2.dist-info/METADATA
telepycrypto-1.0.2.dist-info/WHEEL
telepycrypto-1.0.2.dist-info/top_level.txt
telepycrypto-1.0.2.dist-info/RECORD
