Metadata-Version: 2.1
Name: telepycrypto
Version: 1.0.2
Summary: soon
Home-page: UNKNOWN
Author: Redpiar
Author-email: Regeonwix@gmail.com
License: UNKNOWN
Platform: UNKNOWN
Classifier: Programming Language :: Python :: 3
Classifier: License :: OSI Approved :: MIT License
Classifier: Operating System :: OS Independent
Requires-Python: >=3.6
